bank/__init__.py
bank/account_logic.py
bank/cli/__init__.py
bank/cli/app.py
bank/cli/parsers.py
bank/cli/types.py
bank/exceptions.py
bank/orm.py
bank/settings.py
bank/system/__init__.py
bank/system/shell.py
bank/system/slurm.py
bank/system/smtp.py
crc_bank-0.2.10.dist-info/METADATA
crc_bank-0.2.10.dist-info/WHEEL
crc_bank-0.2.10.dist-info/entry_points.txt
crc_bank-0.2.10.dist-info/RECORD
