Metadata-Version: 2.1
Name: crc-bank
Version: 0.2.10
Summary: Banking application for resource allocation in Slurm based HPC systems.
Home-page: https://github.com/pitt-crc/bank
Keywords: Pitt,CRC,HPC,banking,slurm
Author: Pitt Center for Research Computing
Requires-Python: >=3.8,<4.0
Classifier: Environment :: Console
Classifier: Intended Audience :: System Administrators
Classifier: Natural Language :: English
Classifier: Operating System :: POSIX :: Linux
Classifier: Programming Language :: Python :: 3
Classifier: Programming Language :: Python :: 3.8
Classifier: Programming Language :: Python :: 3.9
Classifier: Programming Language :: Python :: 3.10
Classifier: Programming Language :: Python :: 3.11
Classifier: Programming Language :: Python :: 3.12
Classifier: Topic :: System :: Systems Administration
Classifier: Typing :: Typed
Requires-Dist: SQLAlchemy (==2.0.21)
Requires-Dist: beautifulsoup4 (==4.12.2)
Requires-Dist: pandas (==2.0.3)
Requires-Dist: prettytable (==3.9.0)
Requires-Dist: python-environ (==0.4.54)
Requires-Dist: sqlalchemy-utils (==0.41.1)
Requires-Dist: time-machine (==2.13.0)
Project-URL: Documentation, https://crc-pages.pitt.edu/bank/
Project-URL: Repository, https://github.com/pitt-crc/bank
